[
  {
    "id" : 0,
    "name" : "dutch",
    "code" : "nl-NL",
    "zip" : "dutch",
    "comments" : "",
    "information" : "eeuw ieuw sch eeu aai oei ooi ij aa ui oo eu ei ee ie ou au oe ai EEUW IEUW SCH EEU AAI OEI OOI IJ AA UI OO EU EI EE IE OU AU OE AI Eeuw Ieuw Sch Eeu Aai Oei Ooi Ij Aa Ui Oo Eu Ei Ee Ie Ou Au Oe Ai",
    "method" : [
      {
        "id" : 0,
        "name" : "Kinderen",
        "developer" : "Bartiméus Education",
        "information" : "Voor kinderen. ",
        "letters" : "",
        "comments" : "",
        "lesson" : [
          {
            "id" : 0,
            "name" : "bal",
            "letters" : "bal",
            "sentence" : [],
            "comments" : "",
            "information" : ""
          },
          {
            "id" : 1,
            "name" : "kam",
            "letters" : "kam",
            "sentence" : [],
            "comments" : "…",
            "information" : ".."
          },
          {
            "id" : 2,
            "name" : "kam+",
            "letters" : "balkam",
            "sentence" : [],
            "comments" : "",
            "information" : ""
          },
          {
            "id" : 3,
            "name" : "aap",
            "letters" : "aap",
            "sentence" : [],
            "comments" : "",
            "information" : ""
          },
          {
            "id" : 4,
            "name" : "aap+",
            "letters" : "balkamaap",
            "sentence" : [],
            "comments" : "",
            "information" : ""
          },
          {
            "id" : 5,
            "name" : "bel",
            "letters" : "bel",
            "sentence" : [],
            "comments" : "",
            "information" : ""
          },
          {
            "id" : 6,
            "name" : "bel+",
            "letters" : "balkamaapbel",
            "sentence" : [],
            "comments" : "",
            "information" : ""
          },
          {
            "id" : 7,
            "name" : "deeg",
            "letters" : "deeg",
            "sentence" : [],
            "comments" : "",
            "information" : ""
          },
          {
            "id" : 8,
            "name" : "deeg +",
            "letters" : "balkamaapbeldeeg",
            "sentence" : [],
            "comments" : "",
            "information" : ""
          }
        ]
      },
      {
        "id" : 1,
        "name" : "Volwassen",
        "developer" : "VISIO",
        "information" : "Voor mensen die kunnen lezen en schrijven. ",
        "letters" : "",
        "comments" : "",
        "lesson" : [
            {
              "id": 0,
              "name": "abkl",
              "letters": "abkl",
              "sentence": [],
              "comments": "",
              "information": ""
            },
            {
              "id": 1,
              "name": "cgop",
              "letters": "cgop",
              "sentence": [],
              "comments": "",
              "information": ""
            },
            {
              "id": 2,
              "name": "cgop+",
              "letters": "abklcgop",
              "sentence": [],
              "comments": "",
              "information": ""
            },
            {
              "id": 3,
              "name": "efmv",
              "letters": "efmv",
              "sentence": [],
              "comments": "",
              "information": ""
            },
            {
              "id": 4,
              "name": "efmv+",
              "letters": "abklcgopefmv",
              "sentence": [],
              "comments": "",
              "information": ""
            },
            {
              "id": 5,
              "name": "idur",
              "letters": "idur",
              "sentence": [],
              "comments": "",
              "information": ""
            },
            {
              "id": 6,
              "name": "idur+",
              "letters": "abklcgopefmvidur",
              "sentence": [],
              "comments": "",
              "information": ""
            },
            {
              "id": 7,
              "name": "hsnw+",
              "letters": "abklcgopefmvidurhsnw",
              "sentence": [],
              "comments": "",
              "information": ""
            },
            {
              "id": 8,
              "name": "gklm+",
              "letters": "abklcgopefmvidurhsnwgklm",
              "sentence": [],
              "comments": "",
              "information": ""
            },
            {
              "id": 9,
              "name": "vbchu+",
              "letters": "abklcgopefmvidurhsnwgklmvbchu",
              "sentence": [],
              "comments": "",
              "information": ""
            },
            {
              "id": 10,
              "name": "jtz+",
              "letters": "abklcgopefmvidurhsnwgklmvbchujtz",
              "sentence": [],
              "comments": "",
              "information": ""
            },
            {
              "id": 11,
              "name": "xyqé+",
              "letters": "abklcgopefmvidurhsnwgklmvbchujtzxyqé",
              "sentence": [],
              "comments": "",
              "information": ""
            }
          ]
      },
      {
        "id" : 2,
        "name" : "Vintage",
        "developer" : "Zwijsen",
        "information" : "",
        "letters" : "",
        "comments" : "",
        "lesson" : [
            {
              "id": 0,
              "name": "boom roos",
              "letters": "boomroos",
              "sentence": [],
              "comments": "?",
              "information": "?"
            },
            {
              "id": 1,
              "name": "vis vuur",
              "letters": "visvuur",
              "sentence": [],
              "comments": "?",
              "information": "?"
            },
            {
              "id": 2,
              "name": "mus pim",
              "letters": "muspim",
              "sentence": [],
              "comments": "?",
              "information": "?"
            },
            {
              "id": 3,
              "name": "school raam",
              "letters": "schoolraam",
              "sentence": [],
              "comments": "?",
              "information": "?"
            },
            {
              "id": 4,
              "name": "kees miep",
              "letters": "keesmiep",
              "sentence": [],
              "comments": "?",
              "information": "?"
            },
            {
              "id": 5,
              "name": "bel boek",
              "letters": "belboek",
              "sentence": [],
              "comments": "?",
              "information": "?"
            },
            {
              "id": 6,
              "name": "oom bram",
              "letters": "oombram",
              "sentence": [],
              "comments": "?",
              "information": "?"
            },
            {
              "id": 7,
              "name": "eet aap",
              "letters": "eetaap",
              "sentence": [],
              "comments": "?",
              "information": "?"
            },
            {
              "id": 8,
              "name": "pet wim",
              "letters": "petwim",
              "sentence": [],
              "comments": "?",
              "information": "?"
            },
            {
              "id": 9,
              "name": "bus kar",
              "letters": "buskar",
              "sentence": [],
              "comments": "?",
              "information": "?"
            },
            {
              "id": 10,
              "name": "tol net",
              "letters": "tolnet",
              "sentence": [],
              "comments": "?",
              "information": "?"
            },
            {
              "id": 11,
              "name": "vaar weeg",
              "letters": "vaarweeg",
              "sentence": [],
              "comments": "?",
              "information": "?"
            },
            {
              "id": 12,
              "name": "loop ik",
              "letters": "loopik",
              "sentence": [],
              "comments": "?",
              "information": "?"
            },
            {
              "id": 13,
              "name": "zit een",
              "letters": "ziteen",
              "sentence": [],
              "comments": "?",
              "information": "?"
            },
            {
              "id": 14,
              "name": "twee drie",
              "letters": "tweedrie",
              "sentence": [],
              "comments": "?",
              "information": "?"
            },
            {
              "id": 15,
              "name": "vier vijf",
              "letters": "viervijf",
              "sentence": [],
              "comments": "?",
              "information": "?"
            }
          ]
      }
    ]
  },
  {
    "id" : 1,
    "name" : "english",
    "code" : "nl-NL",
    "zip" : "english",
    "comments" : "",
    "information" : "eeuw ieuw sch eeu aai oei ooi ij aa ui oo eu ei ee ie ou au oe ai EEUW IEUW SCH EEU AAI OEI OOI IJ AA UI OO EU EI EE IE OU AU OE AI Eeuw Ieuw Sch Eeu Aai Oei Ooi Ij Aa Ui Oo Eu Ei Ee Ie Ou Au Oe Ai",
    "method" : [
      {
        "id" : 0,
        "name" : "Dot by dot",
        "developer" : "Bartiméus Education",
        "information" : "Voor kinderen. ",
        "letters" : "",
        "comments" : "",
        "lesson" : [
          {
            "id" : 0,
            "name" : "bal",
            "letters" : "bal",
            "sentence" : [],
            "comments" : "",
            "information" : ""
          },
          {
            "id" : 1,
            "name" : "kam",
            "letters" : "kam",
            "antiletters" : "",
            "sentence" : [],
            "comments" : "…",
            "information" : ".."
          },
          {
            "id" : 2,
            "name" : "kam+",
            "letters" : "balkam",
            "sentence" : [],
            "comments" : "…",
            "information" : ".."
          },
          {
            "id" : 3,
            "name" : "aap-bl",
            "letters" : "aaplb",
            "sentence" : [],
            "comments" : "…",
            "information" : "…"
          },
          {
            "id" : 4,
            "name" : "aap+",
            "letters" : "balkamaap",
            "antiletters" : "",
            "words" : "",
            "allwords" : "",
            "sentence" : [
              "bal bal bal la bla la",
              "bla lab l b a a la"
            ],
            "comments" : "…",
            "information" : "…",
            "voice" : [
              "bal.mp3",
              "bla.mp3"
            ],
            "audio" : [
              "bal.mp3"
            ]
          }
        ]
      }
    ]
  }
]
